{
  "libraryDetailData": {
    "imageURL": "https://pr-cbs.ru/documents/20126/2899196/2.jpg/56b57e51-b91c-bd93-b0d8-f3a92175ea62?t=1665495039521",
    "libName": "Библиотека на Карповке",
    "timeOpen": "",
    "libLoc": "Санкт-Петербург, наб. реки Карповки, д. 28​​",
    "libId": 4,
    "libDesc": "Библиотека на Карповке – это очередной проект модернизации библиотечного пространства на Петроградской стороне. Библиотека, расположенная в самом сердце исторического Петербурга на берегу тихой Карповки, может стать для жителей города и Петроградского района маленьким оазисом, где можно укрыться от суеты мегаполиса и стать ближе к себе, к природе, к книгам. В новом дизайне библиотека стала одним из элементов, формирующих общественное пространство на набережной реки Карповки, основной смысл которого состоит в том, чтобы времяпровождение жителей района становилось удобным, комфортным и наполненным смыслом. Книжный фонд насчитывает более 40 тысяч изданий и ведёт свою историю с 1957 года. В библиотеке любой желающий найдет классику и новинки художественной литературы, актуальный non-fiction, детскую литературу и книги young adult.",
    "imagesList": [
      "https://pr-cbs.ru/documents/20126/2899196/gl.jpg/0df58f18-f7f7-fa6f-5380-a87f18dd8c35?t=1666595941044",
      "https://pr-cbs.ru/documents/20126/2899196/3.jpg/37d65a24-aa3b-bc35-c1aa-527de0cf6062?t=1665495040029",
      "https://pr-cbs.ru/documents/20126/2899196/4.jpg/6ba5e52f-8d3c-6293-523d-4e1429a1ac81?t=1665495040408",
      "https://pr-cbs.ru/documents/20126/2899196/5.jpg/defd8b2b-f71c-9a17-a58b-1200737c217f?t=1665495040842",
      "https://pr-cbs.ru/documents/20126/2899196/6.jpg/d0adc090-a400-a506-f748-579605cef607?t=1665495041467",
      "https://pr-cbs.ru/documents/20126/2899196/7.jpg/db8857a9-4339-bc05-65d5-42b6178ad82b?t=1665495041945",
      "https://pr-cbs.ru/documents/20126/2899196/8.jpg/b03570e4-de0a-de2f-fc62-6f4fd1eb9323?t=1665495043154",
      "https://pr-cbs.ru/documents/20126/2899196/9.jpg/328b1a80-3087-ad19-b0c8-a7e03f7774f2?t=1665495043894"
    ],
    "libLink": "https://pr-cbs.ru/libkarpovka"
  }
}
